rbxwrap/__init__.py
rbxwrap-0.0.1.dist-info/METADATA
rbxwrap-0.0.1.dist-info/WHEEL
rbxwrap-0.0.1.dist-info/top_level.txt
rbxwrap-0.0.1.dist-info/RECORD
