Metadata-Version: 2.1
Name: rbxwrap
Version: 0.0.1
Summary: RBLXWrap.py a simple roblox api wrapper that is easy to write in by <@623612991568478239>
Author: dex
